importchecker/__init__.py
importchecker/importchecker.py
importchecker/tests/__init__.py
importchecker/tests/test_importchecker.py
importchecker/tests/fixture/absimport.py
importchecker/tests/fixture/absimportattrassignment.py
importchecker/tests/fixture/absimportinfunction.py
importchecker/tests/fixture/attrassignment.py
importchecker/tests/fixture/callimportedname.py
importchecker/tests/fixture/fromimport.py
importchecker/tests/fixture/fromimportas.py
importchecker-3.0.dist-info/LICENSE.rst
importchecker-3.0.dist-info/METADATA
importchecker-3.0.dist-info/WHEEL
importchecker-3.0.dist-info/entry_points.txt
importchecker-3.0.dist-info/top_level.txt
importchecker-3.0.dist-info/RECORD
