Metadata-Version: 2.1
Name: importchecker
Version: 3.0
Summary: Importchecker finds unused imports in Python modules.
Home-page: https://github.com/zopefoundation/importchecker
Author: Jan-Wijbrand Kolman
Author-email: zope-dev@zope.dev
License: ZPL 2.1
Classifier: Development Status :: 5 - Production/Stable
Classifier: Environment :: Console
Classifier: Intended Audience :: Developers
Classifier: License :: OSI Approved :: Zope Public License
Classifier: Natural Language :: English
Classifier: Operating System :: OS Independent
Classifier: Programming Language :: Python
Classifier: Programming Language :: Python :: 3
Classifier: Programming Language :: Python :: 3.7
Classifier: Programming Language :: Python :: 3.8
Classifier: Programming Language :: Python :: 3.9
Classifier: Programming Language :: Python :: 3.10
Classifier: Programming Language :: Python :: 3.11
Classifier: Programming Language :: Python :: Implementation :: CPython
Requires-Python: >=3.7
License-File: LICENSE.rst
Requires-Dist: setuptools
Provides-Extra: test
Requires-Dist: zope.testrunner ; extra == 'test'
